{"dataVersion":"cdf14d767fe0","schemaVersion":1,"kind":"zombie","codename":"iceage_hunter_veteran","catalogRole":"official","availability":{"feature":true,"props":true,"almanac":true},"references":{"feature":{"source":"Features/ZombieFeatures.json:ZOMBIES","resolvedPath":"Features/ZombieFeatures.json:ZOMBIES[CODENAME=iceage_hunter_veteran]"},"props":{"source":"Objects/ZombieProps.json:objects","rtid":"RTID(iceage_hunter_veteran@ZombieProps)","requestedAlias":"iceage_hunter_veteran","resolvedAlias":"iceage_hunter_veteran","resolvedPath":"Objects/ZombieProps.json:objects[alias=iceage_hunter_veteran]"},"almanac":{"source":"Objects/ZombieAlmanac.json:objects","rtid":"RTID(iceage_hunter_veteran@ZombieAlmanac)","requestedAlias":"iceage_hunter_veteran","resolvedAlias":"iceage_hunter_veteran","resolvedPath":"Objects/ZombieAlmanac.json:objects[alias=iceage_hunter_veteran]"}},"warnings":[],"feature":{"NAME":{"en":"Hunter Leader Zombie","zh":"猎人领袖僵尸"},"_CARDSPRITENAME":"iceagehunterveteran","CODENAME":"iceage_hunter_veteran","OBTAINWORLD":"ice","ALMANAC":"RTID(iceage_hunter_veteran@ZombieAlmanac)","PROPS":"RTID(iceage_hunter_veteran@ZombieProps)","RES":"IceageHunterVeteran"},"props":{"objclass":"ZombieProperties","aliases":["iceage_hunter_veteran"],"objdata":{"SnowballType":"hunter_snowball","ChillInsteadOfFreeze":true,"WalkSPS":0.2,"EatDPS":150,"Toughness":1100,"LobInterval":3,"LobIntervalAdditional":0.5,"WavePointCost":700,"Weight":2500,"HitRect":"RTID(CommonHitRect@RectangleProps)","AttackRect":"RTID(CommonAttackRect@RectangleProps)"}},"almanac":{"aliases":["iceage_hunter_veteran"],"objclass":"ZombieAlmanacProperties","objdata":{"Elements":[{"TYPE":"TOUGHNESS","SORT":{"en":"Dense","zh":"结实"},"PROGRESS":0.6},{"TYPE":"SPEED","SORT":{"en":"Basic","zh":"普通"},"PROGRESS":0.5}],"Introduction":{"en":"Zombie that can throw snow balls towards his farthest target.","zh":"可以朝本行最远的目标投掷雪球。"},"Special":[{"NAME":{"en":"Special","zh":"特点"},"DESCRIPTION":{"en":"snow balls cool down plants until they freeze into blocks","zh":"雪球能冷冻植物，直到植物被冻成冰块"}}],"Chat":{"en":"He won everyone else cuz no one is willing to be touched by his sparky helmet.","zh":"他能称霸是因为没人想碰到他那满是刺的头盔。"},"DisplayOffset":{"x":15,"y":0},"DisplayScale":{"x":1,"y":1}}}}