{"dataVersion":"360523652dfe","schemaVersion":1,"kind":"plant","codename":"enforcemint","catalogRole":"official","availability":{"feature":true,"props":true,"almanac":true},"references":{"feature":{"source":"Features/PlantFeatures.json:PLANTS","resolvedPath":"Features/PlantFeatures.json:PLANTS[CODENAME=enforcemint]"},"props":{"source":"Objects/PlantProps.json:objects","rtid":"RTID(enforcemint@PlantProps)","requestedAlias":"enforcemint","resolvedAlias":"enforcemint","resolvedPath":"Objects/PlantProps.json:objects[alias=enforcemint]"},"almanac":{"source":"Objects/PlantAlmanac.json:objects","rtid":"RTID(enforcemint@PlantAlmanac)","requestedAlias":"enforcemint","resolvedAlias":"enforcemint","resolvedPath":"Objects/PlantAlmanac.json:objects[alias=enforcemint]"}},"warnings":[],"feature":{"ID":185,"NAME":{"en":"Enforce-mint","zh":"健壮薄荷"},"_CARDSPRITENAME":"mint_melee","CODENAME":"enforcemint","TYPE":["plant","mint","lastStandDisallowed","imitateDisallowed","losingPlant"],"OBTAINWORLD":"mint","ZENGARDEN":{"PlantPlace":"dirt"},"BOOST":0,"COSTUME":0,"ALMANAC":"RTID(enforcemint@PlantAlmanac)","PROPS":"RTID(enforcemint@PlantProps)","RES":{"Disabled":"EnforceMint","Plant":"EnforceMint"}},"props":{"objclass":"PlantProperties","aliases":["enforcemint"],"objdata":{"CannotBeSheepenedByWizard":true,"Cooldown":85,"CooldownFrom":0,"SunCost":0,"BeghouledCost":1000,"Toughness":300,"Family":"Melee","ImmuneToBoomBox":true,"ImmuneToIceblock":true,"Lifespan":18,"ShrinkTime":1.5,"DamageMultiplier":2,"SpeedScale":0.75,"ZombiesToShrink":10,"MintBoostedProps":{"ResistanceMult":1,"SpeedMult":1,"Plantfood":false}}},"almanac":{"aliases":["enforcemint"],"objclass":"PlantAlmanacProperties","objdata":{"Elements":[{"TYPE":"SUNCOST"},{"TYPE":"RECHARGE"},{"TYPE":"DURATION","VALUE":18},{"TYPE":"SPECIAL","SORT":{"en":"Shrinking Zombies","zh":"缩小僵尸"}},{"TYPE":"FAMILY"}],"Introduction":{"en":"Enforce-mints shrink a number of zombies when planted and provide a temporary boost to all Enforce-mint Family plants on the lawn.","zh":"健壮薄荷在种植时缩小场上的好几个僵尸，并为所有健壮家族植物带来增益效果。"},"Special":[],"Chat":{"en":"Enforce-mint shrinks zombies, which may seem a bit off-brand for a guy who's all about melee damage. Enforce-mint shrugs. \"I don't set policy。\" he says.","zh":"健壮薄荷能缩小僵尸，这对一个专精近战伤害的家伙来说似乎有点“人设不符”。健壮薄荷耸了耸肩。对此他表示：“规则不是我定的。”"},"BriefIntroduction":{"en":"Boosts melee plants","zh":"强化近战的植物"},"DisplayOffset":{"x":0,"y":0}}}}