{"dataVersion":"f1d6e1c24b85","schemaVersion":1,"kind":"plant","codename":"sweetpotato","catalogRole":"official","availability":{"feature":true,"props":true,"almanac":true},"references":{"feature":{"source":"Features/PlantFeatures.json:PLANTS","resolvedPath":"Features/PlantFeatures.json:PLANTS[CODENAME=sweetpotato]"},"props":{"source":"Objects/PlantProps.json:objects","rtid":"RTID(sweetpotato@PlantProps)","requestedAlias":"sweetpotato","resolvedAlias":"sweetpotato","resolvedPath":"Objects/PlantProps.json:objects[alias=sweetpotato]"},"almanac":{"source":"Objects/PlantAlmanac.json:objects","rtid":"RTID(sweetpotato@PlantAlmanac)","requestedAlias":"sweetpotato","resolvedAlias":"sweetpotato","resolvedPath":"Objects/PlantAlmanac.json:objects[alias=sweetpotato]"}},"warnings":[],"feature":{"ID":128,"NAME":{"en":"Sweet Potato","zh":"甜薯"},"_CARDSPRITENAME":"sweetpotato","CODENAME":"sweetpotato","TYPE":["plant"],"OBTAINWORLD":"epic","ZENGARDEN":{"PlantPlace":"solid"},"BOOST":2,"COSTUME":1,"ALMANAC":"RTID(sweetpotato@PlantAlmanac)","PROPS":"RTID(sweetpotato@PlantProps)","RES":{"Disabled":"SweetPotato","Plant":"SweetPotato"}},"props":{"objclass":"PlantProperties","aliases":["sweetpotato"],"objdata":{"Cooldown":20,"CooldownFrom":0.75,"SunCost":150,"BeghouledCost":1000,"Toughness":4000,"Family":"Defence","PlantFoodDurationSeconds":6,"PlantfoodAttractWidth":4,"NormalAttractWidth":2,"LaneChangeTime":0.6,"TimeBetweenLaneChanges":5,"AttractsEveryFrame":false,"MintBoostedProps":{"ResistanceMult":3,"SpeedMult":1,"Plantfood":true}}},"almanac":{"aliases":["sweetpotato"],"objclass":"PlantAlmanacProperties","objdata":{"Elements":[{"TYPE":"SUNCOST"},{"TYPE":"RECHARGE"},{"TYPE":"TOUGHNESS"},{"TYPE":"RANGE","SORT":{"en":"Front & Back","zh":"前后"}},{"TYPE":"FAMILY"}],"Introduction":{"en":"Sweet Potatoes attract zombies from other lanes when they are close by.","zh":"甜薯会将相邻行接近的僵尸吸引到本行。"},"Special":[],"Chat":{"en":"Sweet Potato really is as sweet as she looks. Her favorite animal is the unicorn. Her favorite color is (and this is a direct quote) \"all the colors in the rainbow\". When she writes the letter \"i\", she draws a little heart where the dot belongs. Frankly, if it were anyone else, this amount of syrup would be sickening. But on her, well, it just seems right.","zh":"甜薯真的和她看上去那样甜蜜。她最喜欢的动物是独角兽，最喜欢的颜色是（据她所说）“彩虹的颜色”。当她写字母“i”时，她会不自禁在那颗圆点的位置上画颗爱心。说实话，换作是别人像她那样在食物中加糖浆调味，估计会被呛坏，但是对她来说刚刚好。"},"BriefIntroduction":{"en":"Attracts zombies from other lanes when they are close","zh":"吸引相邻行靠近的僵尸"},"DisplayOffset":{"x":0,"y":0}}}}